[
	{
		"name": "King Endymion",
		"unitType": "Civilian",
		"uniqueTo": "Silver Millenium",
		"replaces": "Great General",
		"uniques": [
            "[+35]% Strength bonus for [Military] units within [5] tiles",
			"All adjacent units heal [+40] HP when healing", "[+45] HP when healing",
            "Can instantly construct a [Citadel] improvement <by consuming this unit>",
			"Can be earned through combat",
            "Is part of Great Person group [General]",
            "Great Person - [War]", "Unbuildable", "Uncapturable"],
		"movement": 5
	},
	{
		"name": "Sailor Moon",
		"unitType": "Sailor Guardian",
		"uniqueTo": "Silver Millenium",
		"range": 1,
		"movement": 3,
		"strength": 10,
		"rangedStrength": 15,
		"cost": 90,
		"uniques": ["Limited to [1] per Civilization", "Only available <after adopting [Monarchy]>"],
		"attackSound": "Moon Tiara Boomerang!"
	},
	{
		"name": "Sailor Mercury",
		"unitType": "Sailor Guardian",
		"uniqueTo": "Silver Millenium",
		"range": 1,
		"movement": 3,
		"strength": 8,
		"rangedStrength": 9,
		"cost": 90,
		"uniques": ["[+10]% Strength <vs [Land] units> <when fighting in [Coastal] tiles>", "[+10]% Strength <vs [Land] units> <when fighting in [River] tiles>", "Limited to [1] per Civilization", "Only available <in [Coastal] cities>"],
		"requiredTech": "Sailing",
		"obsoleteTech": "Compass",
		"promotions": ["Quick Study", "Mercury Illusion"],
		"attackSound": "Mercury Aqua Mist!"
	},
	{
		"name": "Sailor Mars",
		"unitType": "Sailor Guardian",
		"uniqueTo": "Silver Millenium",
		"range": 1,
		"movement": 3,
		"strength": 9,
		"rangedStrength": 16,
		"cost": 90,
		"uniques": ["Can see invisible [All] units", "No movement cost to pillage", "Earn [10]% of the damage done to [All] units as [Faith]", "[+35]% Strength <vs [Land] units> <for [10] turns> <upon entering a war with [Major] Civilizations>", "Limited to [1] per Civilization", "Only available <after adopting [Discipline]>"],
		"attackSound": "Moon Tiara Boomerang!"
	}
]
